{
  "kind": "collectionType",
  "collectionName": "defeitos",
  "info": {
    "singularName": "defeito",
    "pluralName": "defeitos",
    "displayName": "Defeitos",
    "description": ""
  },
  "options": {
    "draftAndPublish": true
  },
  "pluginOptions": {},
  "attributes": {
    "classe": {
      "type": "string"
    },
    "endereco": {
      "type": "string"
    },
    "latitude": {
      "type": "float"
    },
    "longitude": {
      "type": "float"
    },
    "dataDeColeta": {
      "type": "string"
    },
    "imagem": {
      "type": "media",
      "multiple": false,
      "required": false,
      "allowedTypes": [
        "images"
      ]
    },
    "quantidade": {
      "type": "integer"
    }
  }
}
